<?xml version="1.0" encoding="UTF-8"?>
<feature
      id="hu.bme.mit.inf.kortargyalo.drones.feature"
      label="Drone Modelling"
      version="1.0.0.qualifier"
      provider-name="Kortargyalo">

   <description url="http://www.example.com/description">
      [Enter Feature Description here.]
   </description>

   <copyright url="http://www.example.com/copyright">
      [Enter Copyright Description here.]
   </copyright>

   <license url="http://www.example.com/license">
      [Enter License Description here.]
   </license>

   <requires>
      <import plugin="org.eclipse.core.runtime"/>
      <import plugin="org.eclipse.emf.edit"/>
      <import plugin="org.eclipse.xtext.common.types"/>
      <import plugin="org.eclipse.xtext.common.types.edit"/>
      <import plugin="org.eclipse.xtext.xbase"/>
      <import plugin="org.eclipse.core.resources"/>
      <import plugin="org.eclipse.emf.ecore.xmi"/>
      <import plugin="org.eclipse.emf.edit.ui"/>
      <import plugin="org.eclipse.ui.ide"/>
      <import plugin="org.eclipse.emf.ecore"/>
      <import plugin="org.eclipse.xtext"/>
      <import plugin="org.eclipse.equinox.common" version="3.5.0" match="greaterOrEqual"/>
      <import plugin="org.eclipse.xtext.xbase.lib"/>
      <import plugin="org.antlr.runtime"/>
      <import plugin="org.eclipse.xtext.util"/>
      <import plugin="org.eclipse.xtend.lib"/>
      <import plugin="org.apache.log4j"/>
      <import plugin="org.eclipse.xtext.ide"/>
      <import plugin="org.eclipse.xtext.xbase.ide"/>
      <import plugin="org.eclipse.xtext.ui"/>
      <import plugin="org.eclipse.xtext.ui.shared"/>
      <import plugin="org.eclipse.xtext.ui.codetemplates.ui"/>
      <import plugin="org.eclipse.ui.editors" version="3.5.0" match="greaterOrEqual"/>
      <import plugin="org.eclipse.ui"/>
      <import plugin="org.eclipse.compare"/>
      <import plugin="org.eclipse.xtext.builder"/>
      <import plugin="org.eclipse.xtext.common.types.ui"/>
      <import plugin="org.eclipse.xtext.xbase.ui"/>
      <import plugin="org.eclipse.jdt.debug.ui"/>
      <import plugin="org.eclipse.core.commands"/>
      <import plugin="org.eclipse.ui.workbench"/>
      <import plugin="org.eclipse.jface"/>
      <import plugin="org.eclipse.equinox.registry"/>
      <import plugin="com.google.guava"/>
      <import plugin="org.eclipse.xtend.lib.macro"/>
      <import plugin="org.eclipse.incquery.runtime" version="1.1.0" match="greaterOrEqual"/>
      <import plugin="org.eclipse.incquery.querybasedfeatures.runtime"/>
      <import plugin="org.eclipse.incquery.validation.core"/>
      <import plugin="org.eclipse.sirius"/>
      <import plugin="org.eclipse.sirius.common.acceleo.aql"/>
      <import plugin="org.eclipse.emf.ecore.editor" version="2.11.0" match="greaterOrEqual"/>
      <import plugin="org.eclipse.pde.core" version="3.10.102" match="greaterOrEqual"/>
      <import plugin="org.eclipse.sirius.ui" version="3.1.4" match="greaterOrEqual"/>
      <import plugin="org.eclipse.emf.transaction" version="1.9.0" match="greaterOrEqual"/>
      <import plugin="org.eclipse.debug.core" version="3.10.0" match="greaterOrEqual"/>
      <import plugin="org.eclipse.debug.ui" version="3.11.101" match="greaterOrEqual"/>
      <import plugin="org.eclipse.jdt.launching" version="3.8.0" match="greaterOrEqual"/>
      <import plugin="org.eclipse.pde.launching" version="3.6.301" match="greaterOrEqual"/>
      <import plugin="org.eclipse.pde.ui" version="3.8.202" match="greaterOrEqual"/>
   </requires>

   <plugin
         id="desmoj"
         download-size="0"
         install-size="0"
         version="0.0.0"/>

   <plugin
         id="hu.bme.mit.inf.kortargyalo.drones.behavior.edit"
         download-size="0"
         install-size="0"
         version="0.0.0"
         unpack="false"/>

   <plugin
         id="hu.bme.mit.inf.kortargyalo.drones.behavior.editor"
         download-size="0"
         install-size="0"
         version="0.0.0"
         unpack="false"/>

   <plugin
         id="hu.bme.mit.inf.kortargyalo.drones.behavior.model"
         download-size="0"
         install-size="0"
         version="0.0.0"
         unpack="false"/>

   <plugin
         id="hu.bme.mit.inf.kortargyalo.drones.behavior.xtext"
         download-size="0"
         install-size="0"
         version="0.0.0"
         unpack="false"/>

   <plugin
         id="hu.bme.mit.inf.kortargyalo.drones.behavior.xtext.ide"
         download-size="0"
         install-size="0"
         version="0.0.0"
         unpack="false"/>

   <plugin
         id="hu.bme.mit.inf.kortargyalo.drones.behavior.xtext.ui"
         download-size="0"
         install-size="0"
         version="0.0.0"
         unpack="false"/>

   <plugin
         id="hu.bme.mit.inf.kortargyalo.drones.behavior.xtext.xtext2xmi"
         download-size="0"
         install-size="0"
         version="0.0.0"
         unpack="false"/>

   <plugin
         id="hu.bme.mit.inf.kortargyalo.drones.simulation.application"
         download-size="0"
         install-size="0"
         version="0.0.0"
         unpack="false"/>

   <plugin
         id="hu.bme.mit.inf.kortargyalo.drones.simulation.model"
         download-size="0"
         install-size="0"
         version="0.0.0"
         unpack="false"/>

   <plugin
         id="hu.bme.mit.inf.kortargyalo.drones.simulation.model.edit"
         download-size="0"
         install-size="0"
         version="0.0.0"
         unpack="false"/>

   <plugin
         id="hu.bme.mit.inf.kortargyalo.drones.simulation.runtime"
         download-size="0"
         install-size="0"
         version="0.0.0"
         unpack="false"/>

   <plugin
         id="hu.bme.mit.inf.kortargyalo.drones.structure.edit"
         download-size="0"
         install-size="0"
         version="0.0.0"
         unpack="false"/>

   <plugin
         id="hu.bme.mit.inf.kortargyalo.drones.structure.editor"
         download-size="0"
         install-size="0"
         version="0.0.0"
         unpack="false"/>

   <plugin
         id="hu.bme.mit.inf.kortargyalo.drones.structure.model"
         download-size="0"
         install-size="0"
         version="0.0.0"
         unpack="false"/>

   <plugin
         id="hu.bme.mit.inf.kortargyalo.drones.structure.model.validation"
         download-size="0"
         install-size="0"
         version="0.0.0"
         unpack="false"/>

   <plugin
         id="hu.bme.mit.inf.kortargyalo.drones.structure.sirius"
         download-size="0"
         install-size="0"
         version="0.0.0"
         unpack="false"/>

   <plugin
         id="hu.bme.mit.inf.kortargyalo.drones.structure.xtext"
         download-size="0"
         install-size="0"
         version="0.0.0"
         unpack="false"/>

   <plugin
         id="hu.bme.mit.inf.kortargyalo.drones.structure.xtext.ui"
         download-size="0"
         install-size="0"
         version="0.0.0"
         unpack="false"/>

   <plugin
         id="hu.bme.mit.inf.kortargyalo.drones.tooling"
         download-size="0"
         install-size="0"
         version="0.0.0"
         unpack="false"/>

   <plugin
         id="hu.bme.mit.inf.kortargyalo.drones.tooling.ui"
         download-size="0"
         install-size="0"
         version="0.0.0"
         unpack="false"/>

</feature>
